odoo8_addon_account_invoice_pricelist_sale-8.0.1.0.0.99.dev3-py2.7-nspkg.pth
odoo8_addon_account_invoice_pricelist_sale-8.0.1.0.0.99.dev3.dist-info/METADATA
odoo8_addon_account_invoice_pricelist_sale-8.0.1.0.0.99.dev3.dist-info/RECORD
odoo8_addon_account_invoice_pricelist_sale-8.0.1.0.0.99.dev3.dist-info/WHEEL
odoo8_addon_account_invoice_pricelist_sale-8.0.1.0.0.99.dev3.dist-info/namespace_packages.txt
odoo8_addon_account_invoice_pricelist_sale-8.0.1.0.0.99.dev3.dist-info/top_level.txt
odoo_addons/account_invoice_pricelist_sale/README.rst
odoo_addons/account_invoice_pricelist_sale/__init__.py
odoo_addons/account_invoice_pricelist_sale/__openerp__.py
odoo_addons/account_invoice_pricelist_sale/i18n/ca.po
odoo_addons/account_invoice_pricelist_sale/i18n/de.po
odoo_addons/account_invoice_pricelist_sale/i18n/el_GR.po
odoo_addons/account_invoice_pricelist_sale/i18n/es.po
odoo_addons/account_invoice_pricelist_sale/i18n/es_VE.po
odoo_addons/account_invoice_pricelist_sale/i18n/fi.po
odoo_addons/account_invoice_pricelist_sale/i18n/fr.po
odoo_addons/account_invoice_pricelist_sale/i18n/hr.po
odoo_addons/account_invoice_pricelist_sale/i18n/hr_HR.po
odoo_addons/account_invoice_pricelist_sale/i18n/hu.po
odoo_addons/account_invoice_pricelist_sale/i18n/it.po
odoo_addons/account_invoice_pricelist_sale/i18n/nl.po
odoo_addons/account_invoice_pricelist_sale/i18n/nl_NL.po
odoo_addons/account_invoice_pricelist_sale/i18n/pt.po
odoo_addons/account_invoice_pricelist_sale/i18n/pt_BR.po
odoo_addons/account_invoice_pricelist_sale/i18n/ro.po
odoo_addons/account_invoice_pricelist_sale/i18n/sl.po
odoo_addons/account_invoice_pricelist_sale/i18n/tr.po
odoo_addons/account_invoice_pricelist_sale/i18n/tr_TR.po
odoo_addons/account_invoice_pricelist_sale/i18n/vi_VN.po
odoo_addons/account_invoice_pricelist_sale/i18n/zh_CN.po
odoo_addons/account_invoice_pricelist_sale/models/__init__.py
odoo_addons/account_invoice_pricelist_sale/models/sale_order.py
odoo_addons/account_invoice_pricelist_sale/static/description/icon.png
odoo_addons/account_invoice_pricelist_sale/static/src/description/icon.png
